keyring_jeepney.py
keyring_jeepney-0.2.dist-info/entry_points.txt
keyring_jeepney-0.2.dist-info/LICENSE
keyring_jeepney-0.2.dist-info/WHEEL
keyring_jeepney-0.2.dist-info/METADATA
keyring_jeepney-0.2.dist-info/RECORD
