Metadata-Version: 1.2
Name: keyring_jeepney
Version: 0.2
Summary: A pure Python keyring backend using the Freedesktop secret service.
Home-page: https://gitlab.com/takluyver/keyring_jeepney
License: UNKNOWN
Author: Thomas Kluyver
Author-email: thomas@kluyver.me.uk
Requires-Python: >=3.5
Classifier: License :: OSI Approved :: MIT License
Classifier: Programming Language :: Python :: 3
Requires-Dist: keyring
Requires-Dist: jeepney >= 0.3
